ucopy/__init__.py
ucopy/ucopy.py
ucopy-1.0.1.data/scripts/ucopy
ucopy-1.0.1.dist-info/LICENSE.txt
ucopy-1.0.1.dist-info/METADATA
ucopy-1.0.1.dist-info/WHEEL
ucopy-1.0.1.dist-info/top_level.txt
ucopy-1.0.1.dist-info/RECORD
