Metadata-Version: 2.1
Name: ucopy
Version: 1.0.1
Summary: Union copier:copy files from one or more dirs to target and autorename files if same already presents
Home-page: https://github.com/Insolita/ucopy
Author: Insolita
Author-email: webmaster100500@ya.ru
License: MIT
Keywords: copy,move,rename
Platform: UNKNOWN
Classifier: Programming Language :: Python :: 3
Classifier: License :: OSI Approved :: MIT License
Classifier: Operating System :: OS Independent
Requires-Python: >=3.7
